yamling/__init__.py
yamling/constructors/__init__.py
yamling/constructors/variable.py
yamling/consts.py
yamling/deepmerge.py
yamling/dump_universal.py
yamling/exceptions.py
yamling/jinja_tag.py
yamling/load_universal.py
yamling/log.py
yamling/py.typed
yamling/typedefs.py
yamling/utils.py
yamling/verify.py
yamling/yaml_dumpers.py
yamling/yaml_loaders.py
yamling/yamlparser.py
yamling-2.0.3.dist-info/licenses/LICENSE
yamling-2.0.3.dist-info/WHEEL
yamling-2.0.3.dist-info/entry_points.txt
yamling-2.0.3.dist-info/METADATA
yamling-2.0.3.dist-info/RECORD
