Metadata-Version: 2.4
Name: yamling
Version: 2.0.3
Summary: Enhanced YAML loading and dumping.
Keywords: PyYAML,include,serialization,yaml,yml
Author: Philipp Temminghoff
Author-email: Philipp Temminghoff <philipptemminghoff@googlemail.com>
License-Expression: MIT
License-File: LICENSE
Classifier: Development Status :: 4 - Beta
Classifier: Intended Audience :: Developers
Classifier: Operating System :: OS Independent
Classifier: Programming Language :: Python :: 3
Classifier: Programming Language :: Python :: 3 :: Only
Classifier: Programming Language :: Python :: 3.12
Classifier: Programming Language :: Python :: 3.13
Classifier: Programming Language :: Python :: 3.14
Classifier: Topic :: Documentation
Classifier: Topic :: Software Development
Classifier: Topic :: Utilities
Classifier: Typing :: Typed
Requires-Dist: pyyaml>=5.1
Requires-Dist: anyenv>=0.4.7
Requires-Dist: fsspec
Requires-Dist: pydantic
Requires-Dist: pyyaml-include
Requires-Dist: universal-pathlib
Requires-Dist: upathtools>=0.6.4
Requires-Dist: jinja2 ; extra == 'all'
Requires-Dist: tomli-w ; extra == 'all'
Requires-Dist: jinja2 ; extra == 'jinja2'
Requires-Dist: tomli-w ; extra == 'toml'
Requires-Python: >=3.13
Project-URL: Code coverage, https://app.codecov.io/gh/phil65/yamling
Project-URL: Discussions, https://github.com/phil65/yamling/discussions
Project-URL: Documentation, https://phil65.github.io/yamling/
Project-URL: Issues, https://github.com/phil65/yamling/issues
Project-URL: Source, https://github.com/phil65/yamling
Provides-Extra: all
Provides-Extra: jinja2
Provides-Extra: toml
